dbt/__init__.py
dbt/adapters/db2_for_i/__init__.py
dbt/adapters/db2_for_i/__version__.py
dbt/adapters/db2_for_i/column.py
dbt/adapters/db2_for_i/connections.py
dbt/adapters/db2_for_i/impl.py
dbt/adapters/db2_for_i/relation.py
dbt/include/db2_for_i/__init__.py
dbt/include/db2_for_i/dbt_project.yml
dbt/include/db2_for_i/macros/adapters.sql
dbt/include/db2_for_i/macros/apply_grants.sql
dbt/include/db2_for_i/macros/catalog.sql
dbt/include/db2_for_i/macros/materializations/incremental/incremental.sql
dbt/include/db2_for_i/macros/materializations/incremental/merge.sql
dbt/include/db2_for_i/macros/materializations/seed/seed.sql
dbt/include/db2_for_i/macros/materializations/snapshot/snapshot.sql
dbt/include/db2_for_i/macros/materializations/snapshot/snapshot_merge.sql
dbt/include/db2_for_i/macros/materializations/snapshot/strategies.sql
dbt/include/db2_for_i/macros/materializations/table/table.sql
dbt/include/db2_for_i/macros/materializations/tests/helpers.sql
dbt/include/db2_for_i/macros/materializations/tests/where_subquery.sql
dbt/include/db2_for_i/macros/materializations/view/view.sql
dbt_db2fori-1.7.9.dist-info/LICENSE
dbt_db2fori-1.7.9.dist-info/METADATA
dbt_db2fori-1.7.9.dist-info/WHEEL
dbt_db2fori-1.7.9.dist-info/RECORD
