Metadata-Version: 2.1
Name: dbt-db2fori
Version: 1.7.9
Summary: dbt adapter for IBM db2 for i
Home-page: https://github.com/kaysef/dbt-db2fori
License: MIT
Author: Seth O
Author-email: sdowusu@gmail.com
Requires-Python: >=3.12,<4.0
Classifier: License :: OSI Approved :: MIT License
Classifier: Programming Language :: Python :: 3
Classifier: Programming Language :: Python :: 3.12
Requires-Dist: dbt-core (>=1.7.11,<2.0.0)
Requires-Dist: pyodbc (>=5.1.0,<6.0.0)
Project-URL: Documentation, https://github.com/kaysef/dbt-db2fori
Project-URL: Repository, https://github.com/kaysef/dbt-db2fori
